LICENSE
README.md
setup.py
roid/__init__.py
roid/__version__.py
roid/app.py
roid/callers.py
roid/checks.py
roid/command.py
roid/components.py
roid/deferred.py
roid/error_handlers.py
roid/exceptions.py
roid/extractors.py
roid/helpers.py
roid/http.py
roid/interactions.py
roid/objects.py
roid/response.py
roid.egg-info/PKG-INFO
roid.egg-info/SOURCES.txt
roid.egg-info/dependency_links.txt
roid.egg-info/requires.txt
roid.egg-info/top_level.txt
roid/state/__init__.py
roid/state/managed.py
roid/state/storage.py